README.md
setup.py
toronto_hydro_green_button.py
toronto_hydro_green_button.egg-info/PKG-INFO
toronto_hydro_green_button.egg-info/SOURCES.txt
toronto_hydro_green_button.egg-info/dependency_links.txt
toronto_hydro_green_button.egg-info/entry_points.txt
toronto_hydro_green_button.egg-info/requires.txt
toronto_hydro_green_button.egg-info/top_level.txt