Metadata-Version: 2.1
Name: toronto-hydro-green-button
Version: 0.1.0
Summary: UNKNOWN
Home-page: https://github.com/benwebber/toronto-hydro-green-button/
Author: Ben Webber
Author-email: benjamin.webber@gmail.com
License: UNKNOWN
Platform: UNKNOWN
Classifier: Development Status :: 4 - Beta
Classifier: License :: OSI Approved :: MIT License
Classifier: Programming Language :: Python :: 3
Classifier: Programming Language :: Python :: 3.6
Classifier: Programming Language :: Python :: 3.7
Classifier: Programming Language :: Python :: 3.8
Classifier: Programming Language :: Python :: 3 :: Only
